dash_bgmgr_redis/__init__.py
dash_bgmgr_redis/redis.py
dash_bgmgr_redis-0.2.0.dist-info/licenses/LICENSE
dash_bgmgr_redis-0.2.0.dist-info/METADATA
dash_bgmgr_redis-0.2.0.dist-info/WHEEL
dash_bgmgr_redis-0.2.0.dist-info/top_level.txt
dash_bgmgr_redis-0.2.0.dist-info/RECORD
