Metadata-Version: 2.4
Name: dash-bgmgr-redis
Version: 0.2.0
Summary: Redis-based background callback manager for Dash applications
Home-page: https://github.com/RazgrizHsu/dash-bgmgr-redis
Author: Razgriz Hsu
Author-email: Razgriz Hsu <dev@raz.tw>
Project-URL: Homepage, https://github.com/RazgrizHsu/dash-bgmgr-redis
Project-URL: Bug Reports, https://github.com/RazgrizHsu/dash-bgmgr-redis/issues
Project-URL: Source, https://github.com/RazgrizHsu/dash-bgmgr-redis
Keywords: dash,redis,background,callback,manager
Classifier: Development Status :: 4 - Beta
Classifier: Intended Audience :: Developers
Classifier: License :: OSI Approved :: MIT License
Classifier: Operating System :: OS Independent
Classifier: Programming Language :: Python :: 3
Classifier: Programming Language :: Python :: 3.7
Classifier: Programming Language :: Python :: 3.8
Classifier: Programming Language :: Python :: 3.9
Classifier: Programming Language :: Python :: 3.10
Classifier: Programming Language :: Python :: 3.11
Classifier: Topic :: Software Development :: Libraries :: Python Modules
Requires-Python: >=3.7
License-File: LICENSE
Requires-Dist: dash<4.0.0,>=3.0.0
Requires-Dist: redis>=5.0.0
Requires-Dist: psutil>=5.0.0
Requires-Dist: multiprocess>=0.70.0
Provides-Extra: dev
Requires-Dist: pytest>=6.0; extra == "dev"
Requires-Dist: pytest-cov; extra == "dev"
Requires-Dist: black; extra == "dev"
Requires-Dist: flake8; extra == "dev"
Requires-Dist: mypy; extra == "dev"
Dynamic: author
Dynamic: home-page
Dynamic: license-file
Dynamic: requires-python
